db_modeler/__init__.py
db_modeler/management/__init__.py
db_modeler/management/commands/__init__.py
db_modeler/management/commands/model_db.py
django_db_modeler-0.1.5.dist-info/LICENSE
django_db_modeler-0.1.5.dist-info/METADATA
django_db_modeler-0.1.5.dist-info/WHEEL
django_db_modeler-0.1.5.dist-info/entry_points.txt
django_db_modeler-0.1.5.dist-info/top_level.txt
django_db_modeler-0.1.5.dist-info/RECORD
