Metadata-Version: 2.1
Name: django-db-modeler
Version: 0.1.5
Summary: A Django management command to generate a graph of a model and its neighbors up to a specified depth.
Home-page: https://github.com/yourusername/django-graph-models-command
Author: Felix Lohrke
Author-email: Sontyp@bin-wieder-da.de
License: MIT
Platform: UNKNOWN
Classifier: Development Status :: 4 - Beta
Classifier: Framework :: Django
Classifier: Intended Audience :: Developers
Classifier: License :: OSI Approved :: MIT License
Classifier: Programming Language :: Python :: 3
Classifier: Programming Language :: Python :: 3.6
Classifier: Programming Language :: Python :: 3.7
Classifier: Programming Language :: Python :: 3.8
Classifier: Programming Language :: Python :: 3.9
Classifier: Programming Language :: Python :: 3.10
Requires-Python: >=3.6
License-File: LICENSE
Requires-Dist: Django (>=3.0)
Requires-Dist: django-extensions (>=3.0)
Requires-Dist: pygraphviz (==1.13)
